{
  "mockpreview": {
    "mockUri": "",
    "metadataFilePath": "",
    "loadJSONFiles": false,
    "loadCustomRequests": false,
    "mockRequestsFilePath": ""
  },
  "deploy": {
    "destination": "ECI_DEV",
    "name": "ZCAROBSERVTRX"
  },
  "projectType": [
    "sap.watt.saptoolsets.fiori.project.ui5template.smartProject",
    "sap.watt.uitools.ide.fiori",
    "com.watt.common.builder.sapui5clientbuild"
  ],
  "build": {
    "buildRequired": true,
    "targetFolder": "dist",
    "lastBuildDateTime": "Tue, 21 Oct 2025 07:27:47 GMT"
  }
}